__init__.py
gql_dynamic_query_builder/__init__.py
gql_dynamic_query_builder/api/__init__.py
gql_dynamic_query_builder/api/builder.py
gql_dynamic_query_builder/api/dsl/__init__.py
gql_dynamic_query_builder/api/dsl/query.py
gql_dynamic_query_builder/api/dsl/building_blocks/__init__.py
gql_dynamic_query_builder/api/dsl/building_blocks/helpers.py
gql_dynamic_query_builder/api/dsl/building_blocks/lazy_where_block.py
gql_dynamic_query_builder/api/dsl/building_blocks/query_block.py
gql_dynamic_query_builder/core/__init__.py
gql_dynamic_query_builder/core/helpers.py
gql_dynamic_query_builder/core/grammar/__init__.py
gql_dynamic_query_builder/core/grammar/parse_actions.py
gql_dynamic_query_builder/core/grammar/query.py
gql_dynamic_query_builder/core/grammar/subquery.py
gql_dynamic_query_builder/core/grammar/where_clause.py
gql_dynamic_query_builder-1.2.0.dist-info/licenses/LICENSE.md
gql_dynamic_query_builder-1.2.0.dist-info/METADATA
gql_dynamic_query_builder-1.2.0.dist-info/WHEEL
gql_dynamic_query_builder-1.2.0.dist-info/top_level.txt
gql_dynamic_query_builder-1.2.0.dist-info/RECORD
