Metadata-Version: 2.4
Name: gql-dynamic-query-builder
Version: 1.2.0
Summary: Dynamic GraphQL query builder
Author-email: msldrr <moritz.soelderer@icloud.com>
License-Expression: MIT
Requires-Python: >=3.10
License-File: LICENSE.md
Requires-Dist: pyparsing>=3.3.2
Provides-Extra: dev
Requires-Dist: pytest>=8.0; extra == "dev"
Requires-Dist: ruff; extra == "dev"
Dynamic: license-file
